coons_cli/__init__.py
coons_cli/cli.py
coons_cli-0.1.0.dist-info/entry_points.txt
coons_cli-0.1.0.dist-info/LICENSE
coons_cli-0.1.0.dist-info/WHEEL
coons_cli-0.1.0.dist-info/METADATA
coons_cli-0.1.0.dist-info/RECORD
