Metadata-Version: 2.1
Name: coons-cli
Version: 0.1.0
Summary: A command line interface for coons.
Home-page: https://github.com/chezjohnny/coons
License: MIT
Author: Johnny Mariéthoz
Author-email: chezjohnny@gmail.com
Requires-Python: >=3.9,<4.0
Classifier: License :: OSI Approved :: MIT License
Classifier: Programming Language :: Python :: 3
Classifier: Programming Language :: Python :: 3.10
Classifier: Programming Language :: Python :: 3.9
Requires-Dist: click (>=8.1.3,<9.0.0)
Requires-Dist: requests (>=2.27.1,<3.0.0)
